mailfox/__init__.py
mailfox/__main__.py
mailfox/email_interface/__init__.py
mailfox/email_interface/email_gen_ai.py
mailfox/email_interface/email_handler.py
mailfox/mailfox.py
mailfox/vector/__init__.py
mailfox/vector/clustering.py
mailfox/vector/database.py
mailfox-0.1.5.dist-info/LICENSE
mailfox-0.1.5.dist-info/METADATA
mailfox-0.1.5.dist-info/WHEEL
mailfox-0.1.5.dist-info/entry_points.txt
mailfox-0.1.5.dist-info/RECORD
