Metadata-Version: 2.1
Name: mailfox
Version: 0.1.5
Summary: Mailfox is a simple and fast ai powered email toolkit to enhance you email workflow
Home-page: https://github.com/stelath/mailfox
License: GNU GPLv3
Author: Alex Korte
Author-email: alex.k.korte@gmail.com
Requires-Python: >=3.8,<4.0
Classifier: License :: Other/Proprietary License
Classifier: Programming Language :: Python :: 3
Classifier: Programming Language :: Python :: 3.8
Classifier: Programming Language :: Python :: 3.9
Classifier: Programming Language :: Python :: 3.10
Classifier: Programming Language :: Python :: 3.11
Classifier: Programming Language :: Python :: 3.12
Requires-Dist: pyyaml (>=6.0,<7.0)
Requires-Dist: typer (>=0.3.2,<1.0.0)
Project-URL: Repository, https://github.com/stelath/mailfox
